AFR/__init__.py
AFR/adjr2_score.py
AFR/aic_score.py
AFR/bic_score.py
AFR/check_betas.py
AFR/checkdata.py
AFR/corsel.py
AFR/dec_plot.py
AFR/finratKZ.py
AFR/macroKZ.py
AFR/opt_size.py
AFR/pt_multi.py
AFR/pt_one.py
AFR/reg_test.py
AFR/regsel_f.py
AFR/sbic_score.py
AFR/vif_reg.py
AFR/load/finratKZ.csv
AFR/load/finratKZ_dataset.rst
AFR/load/macroKZ.csv
AFR/load/macroKZ_dataset.rst
afr-3.0.1.dist-info/licenses/LICENSE.rtf
afr-3.0.1.dist-info/METADATA
afr-3.0.1.dist-info/WHEEL
afr-3.0.1.dist-info/top_level.txt
afr-3.0.1.dist-info/RECORD
