Metadata-Version: 2.4
Name: AFR
Version: 3.0.1
Summary: Statistical toolkit aimed to help statisticians, data analysts, data scientists, bankers and other professionals to analyze financial data
Home-page: https://github.com/AFRKZ/AFR
Author: Timur Abilkassymov, Alua Makhmetova, Sultan Zhaparov
Author-email: sultan.saldau@gmail.com
License: 3-clause BSD
Requires-Python: >=3.7
License-File: LICENSE.rtf
Requires-Dist: setuptools>=66.6.0
Requires-Dist: pandas
Requires-Dist: scikit-learn>=1.3.1
Requires-Dist: numpy
Requires-Dist: statsmodels
Requires-Dist: matplotlib
Requires-Dist: mlxtend
Dynamic: author
Dynamic: author-email
Dynamic: description
Dynamic: description-content-type
Dynamic: home-page
Dynamic: license
Dynamic: license-file
Dynamic: requires-dist
Dynamic: requires-python
Dynamic: summary
